object_compresser/__init__.py
object_compresser/data.py
object_compresser-0.0.0.dist-info/LICENSE.html
object_compresser-0.0.0.dist-info/METADATA
object_compresser-0.0.0.dist-info/WHEEL
object_compresser-0.0.0.dist-info/top_level.txt
object_compresser-0.0.0.dist-info/RECORD
