Metadata-Version: 2.1
Name: object-compresser
Version: 0.0.0
Summary: this is just a symple module to save/load data to/from your file.
Home-page: https://github.com/bhanuponguru/object_compresser.git
Author: bhanu
Author-email: bhanuponguru@gmail.com
License: UNKNOWN
Platform: UNKNOWN
